tiomagic/__init__.py
tiomagic/facade.py
tiomagic/core/__init__.py
tiomagic/core/_jobs.py
tiomagic/core/_validation.py
tiomagic/core/config.py
tiomagic/core/constants.py
tiomagic/core/errors.py
tiomagic/core/registry.py
tiomagic/core/_utils/__init__.py
tiomagic/core/_utils/_modal_helpers.py
tiomagic/core/_utils/_utils.py
tiomagic/core/schemas/__init__.py
tiomagic/core/schemas/image_to_video.py
tiomagic/core/schemas/interpolate.py
tiomagic/core/schemas/pose_guidance.py
tiomagic/core/schemas/text_to_video.py
tiomagic/providers/__init__.py
tiomagic/providers/local/__init__.py
tiomagic/providers/local/base.py
tiomagic/providers/local/luma.py
tiomagic/providers/local/veo.py
tiomagic/providers/modal/__init__.py
tiomagic/providers/modal/base.py
tiomagic/providers/modal/cogvideox_5b.py
tiomagic/providers/modal/cogvideox_5b_i2v.py
tiomagic/providers/modal/framepack_i2v_hy.py
tiomagic/providers/modal/ltx_video.py
tiomagic/providers/modal/pusav1.py
tiomagic/providers/modal/wan_2_1_14b.py
tiomagic/providers/modal/wan_2_1_flf2v_14b_720p.py
tiomagic/providers/modal/wan_2_1_i2v_14b_720p.py
tiomagic/providers/modal/wan_2_1_vace_14b.py
tiomagic-1.0.0.dist-info/METADATA
tiomagic-1.0.0.dist-info/WHEEL
tiomagic-1.0.0.dist-info/licenses/LICENSE
tiomagic-1.0.0.dist-info/RECORD
