Metadata-Version: 2.4
Name: tiomagic
Version: 1.0.0
Summary: A Python package for generating animations using AI-powered video models
Author: Tio Magic Company
License: MIT
License-File: LICENSE
Keywords: ai,animation,diffusers,modal,video-generation
Classifier: Intended Audience :: Developers
Classifier: License :: OSI Approved :: MIT License
Classifier: Programming Language :: Python :: 3
Classifier: Programming Language :: Python :: 3.8
Classifier: Programming Language :: Python :: 3.9
Classifier: Programming Language :: Python :: 3.10
Classifier: Programming Language :: Python :: 3.11
Requires-Python: >=3.8
Requires-Dist: fastapi[standard]
Requires-Dist: google-genai
Requires-Dist: gradio
Requires-Dist: gradio-client
Requires-Dist: lumaai
Requires-Dist: modal
Requires-Dist: numpy
Requires-Dist: pillow
Requires-Dist: python-dotenv
Requires-Dist: requests
Requires-Dist: torch>=2.5.0
Provides-Extra: dev
Requires-Dist: mypy; extra == 'dev'
Requires-Dist: pre-commit; extra == 'dev'
Requires-Dist: pytest-cov; extra == 'dev'
Requires-Dist: pytest>=7.0; extra == 'dev'
Requires-Dist: ruff; extra == 'dev'
